Metadata-Version: 2.1
Name: stduino
Version: 0.1.9
Summary: Stduino IDE For win、mac、linux
Home-page: http://www.stduino.com
Author: 文涛
Author-email: 33672008@qq.com
License: UNKNOWN
Keywords: Stduino IDE
Platform: UNKNOWN
Classifier: Intended Audience :: Developers
Classifier: Operating System :: OS Independent
Classifier: Natural Language :: Chinese (Simplified)
Classifier: Programming Language :: Python
Classifier: Programming Language :: Python :: 3
Classifier: Topic :: Utilities
